password_strength_calculator/__init__.py
password_strength_calculator/script.py
password_strength_calculator-1.0.0.dist-info/METADATA
password_strength_calculator-1.0.0.dist-info/WHEEL
password_strength_calculator-1.0.0.dist-info/top_level.txt
password_strength_calculator-1.0.0.dist-info/RECORD
