Metadata-Version: 2.1
Name: password-strength-calculator
Version: 1.0.0
Summary: A Python package to calculate the score of a password according to its strength
Home-page: https://github.com/blunteshwar/password-score-calculator.git
Author: Piyush Vashisht
Author-email: piyush17303@iiitd.ac.in
License: MIT License
Platform: UNKNOWN
Classifier: Development Status :: 1 - Planning
Classifier: Intended Audience :: Science/Research
Classifier: Operating System :: POSIX :: Linux
Classifier: Programming Language :: Python :: 2
Classifier: Programming Language :: Python :: 2.7
Classifier: Programming Language :: Python :: 3
Classifier: Programming Language :: Python :: 3.4
Classifier: Programming Language :: Python :: 3.5
Requires-Dist: nltk
